src/__init__.py
src/github.py
src/main.py
src/storge.py
src/utils.py
easy_up-1.0.0.dist-info/LICENSE
easy_up-1.0.0.dist-info/METADATA
easy_up-1.0.0.dist-info/WHEEL
easy_up-1.0.0.dist-info/entry_points.txt
easy_up-1.0.0.dist-info/top_level.txt
easy_up-1.0.0.dist-info/RECORD
