Metadata-Version: 2.1
Name: easy-up
Version: 1.0.0
Summary: Useful tool to update installed tools
Home-page: https://github.com/islam-kamel/package_manager
Author: Islam Kamel
Author-email: islam.kamel@agr.svu.edu.eg
License: MIT
Keywords: EasyUp,easyup,easyUp,easyUP,update tools,automation update,automation,package manager
Classifier: Development Status :: 4 - Beta
Classifier: Environment :: Console
Classifier: Intended Audience :: End Users/Desktop
Classifier: License :: OSI Approved :: MIT License
Classifier: Operating System :: Microsoft :: Windows
Classifier: Programming Language :: Python :: 3
Classifier: Programming Language :: Python :: 3 :: Only
Classifier: Programming Language :: Python :: 3.7
Classifier: Programming Language :: Python :: 3.8
Classifier: Programming Language :: Python :: 3.9
Classifier: Programming Language :: Python :: 3.10
Classifier: Programming Language :: Python :: Implementation :: CPython
Classifier: Topic :: Home Automation
Classifier: Topic :: Terminals
Requires-Python: >=3.7
License-File: LICENSE
Requires-Dist: requests
Requires-Dist: click
Requires-Dist: tqdm
